<?xml version="1.0" encoding="utf-8"?>
<WwiseDocument Type="UserProjectSettings" SchemaVersion="70">
	<UserProjectSettingsInfo>
		<UserProjectSettings Name="" ID="{3C9876A0-4D03-459D-9F50-E1466FED16D3}">
			<PropertyList>
				<Property Name="ExternalSourcesInputPath" Type="string">
					<ValueList>
						<Value Platform="Windows"></Value>
						<Value Platform="Linux"></Value>
						<Value Platform="Mac"></Value>
					</ValueList>
				</Property>
				<Property Name="ExternalSourcesOutputPath" Type="string">
					<ValueList>
						<Value Platform="Windows">GeneratedSoundBanks\Windows\</Value>
						<Value Platform="Linux">GeneratedSoundBanks\Linux\</Value>
						<Value Platform="Mac">GeneratedSoundBanks\Mac\</Value>
					</ValueList>
				</Property>
				<Property Name="SoundBankHeaderFilePath" Type="string" Value="GeneratedSoundBanks\"/>
				<Property Name="SoundBankPaths" Type="string">
					<ValueList>
						<Value Platform="Windows">GeneratedSoundBanks\Windows\</Value>
						<Value Platform="Linux">GeneratedSoundBanks\Linux\</Value>
						<Value Platform="Mac">GeneratedSoundBanks\Mac\</Value>
					</ValueList>
				</Property>
				<Property Name="SoundBankPostGenerateCustomCmdDescription" Type="string">
					<ValueList>
						<Value Platform="Windows">Copy Streamed Files</Value>
						<Value Platform="Linux">Copy Streamed Files</Value>
						<Value Platform="Mac">Copy Streamed Files</Value>
					</ValueList>
				</Property>
				<Property Name="SoundBankPostGenerateCustomCmdLines" Type="string">
					<ValueList>
						<Value Platform="Windows">"$(WwiseExePath)\CopyStreamedFiles.exe" -info "$(InfoFilePath)" -outputpath "$(SoundBankPath)" -banks "$(SoundBankListAsTextFile)" -languages "$(LanguageList)"</Value>
						<Value Platform="Linux">"$(WwiseExePath)\CopyStreamedFiles.exe" -info "$(InfoFilePath)" -outputpath "$(SoundBankPath)" -banks "$(SoundBankListAsTextFile)" -languages "$(LanguageList)"</Value>
						<Value Platform="Mac">"$(WwiseExePath)\CopyStreamedFiles.exe" -info "$(InfoFilePath)" -outputpath "$(SoundBankPath)" -banks "$(SoundBankListAsTextFile)" -languages "$(LanguageList)"</Value>
					</ValueList>
				</Property>
				<Property Name="SoundBankPreGenerateCustomCmdDescription" Type="string">
					<ValueList>
						<Value Platform="Windows"></Value>
						<Value Platform="Linux"></Value>
						<Value Platform="Mac"></Value>
					</ValueList>
				</Property>
				<Property Name="SoundBankPreGenerateCustomCmdLines" Type="string">
					<ValueList>
						<Value Platform="Windows"></Value>
						<Value Platform="Linux"></Value>
						<Value Platform="Mac"></Value>
					</ValueList>
				</Property>
			</PropertyList>
			<PluginInnerObjectList>
				<List Name="BatchRenameSettings">
					<PluginInnerObject Name="" ID="{2FD9EA00-593D-4238-B256-40259DCE14F9}" PluginName="BatchRenameSettings" CompanyID="0" PluginID="992">
						<PropertyList>
							<Property Name="EnableInsert" Type="bool" Value="True"/>
							<Property Name="EnableRemove" Type="bool" Value="True"/>
							<Property Name="InsertStartAt" Type="int32" Value="1"/>
							<Property Name="InsertToInsert" Type="string" Value="Impact General %d"/>
							<Property Name="InsertWhat" Type="int16" Value="1"/>
							<Property Name="RemoveCount" Type="int32" Value="82"/>
							<Property Name="insertFrom" Type="int16" Value="0"/>
						</PropertyList>
					</PluginInnerObject>
				</List>
			</PluginInnerObjectList>
		</UserProjectSettings>
	</UserProjectSettingsInfo>
</WwiseDocument>
